CHANGES.rst
README.rst
setup.py
collective/__init__.py
collective.portlet.geo.egg-info/PKG-INFO
collective.portlet.geo.egg-info/SOURCES.txt
collective.portlet.geo.egg-info/dependency_links.txt
collective.portlet.geo.egg-info/entry_points.txt
collective.portlet.geo.egg-info/namespace_packages.txt
collective.portlet.geo.egg-info/not-zip-safe
collective.portlet.geo.egg-info/requires.txt
collective.portlet.geo.egg-info/top_level.txt
collective/portlet/__init__.py
collective/portlet/geo/__init__.py
collective/portlet/geo/configure.zcml
collective/portlet/geo/controlpanel.py
collective/portlet/geo/database.py
collective/portlet/geo/i18n.py
collective/portlet/geo/interfaces.py
collective/portlet/geo/link.pt
collective/portlet/geo/portlets.py
collective/portlet/geo/security.py
collective/portlet/geo/setuphandlers.py
collective/portlet/geo/utils.py
collective/portlet/geo/vocabularies.py
collective/portlet/geo/wrapper.pt
collective/portlet/geo/profiles/default/controlpanel.xml
collective/portlet/geo/profiles/default/import_steps.xml
collective/portlet/geo/profiles/default/metadata.xml
collective/portlet/geo/profiles/default/portlets.xml
collective/portlet/geo/profiles/default/registry.xml
collective/portlet/geo/static/ip2country.csv.gz