Metadata-Version: 1.1
Name: collective.portlet.geo
Version: 1.0
Summary: Wrap any Plone portlet with geolocation or language negotiation.
Home-page: http://plone.org/products/collective.portlet.geo
Author: Malthe Borch
Author-email: mborch@gmail.com
License: GPL
Keywords: plone portlet geolocation
Platform: UNKNOWN
Classifier: Framework :: Plone
Classifier: Framework :: Zope2
Classifier: Framework :: Zope3
Classifier: Programming Language :: Python
Classifier: Topic :: Software Development :: Libraries :: Python Modules
